notification_timer/__init__.py
notification_timer/feed.py
notification_timer/notification.py
notification_timer-1.0.1.dist-info/LICENSE
notification_timer-1.0.1.dist-info/METADATA
notification_timer-1.0.1.dist-info/WHEEL
notification_timer-1.0.1.dist-info/entry_points.txt
notification_timer-1.0.1.dist-info/top_level.txt
notification_timer-1.0.1.dist-info/RECORD
