Metadata-Version: 2.1
Name: notification-timer
Version: 1.0.1
Summary: Package To Push Notification and Keep User Motivated
Home-page: https://github.com/TheMLEngineer/notification_timer
Author: KARTHIKEYAN MUTHU
Author-email: phenomenalkarthikeyan@gmail.com
License: MIT
Platform: UNKNOWN
Classifier: Programming Language :: Python :: 3
Classifier: License :: OSI Approved :: MIT License
Classifier: Operating System :: OS Independent
Requires-Python: >=3.6
Requires-Dist: time
Requires-Dist: os
Requires-Dist: subprocess
